Golang101Hacks/README.md
Golang101Hacks/__init__.py
Golang101Hacks/__main__.py
Golang101Hacks/file.epub
Golang101Hacks/index.html
Golang101Hacks/css/__init__.py
Golang101Hacks/css/annotations.css
Golang101Hacks/css/main.css
Golang101Hacks/css/normalize.css
Golang101Hacks/css/popup.css
Golang101Hacks/font/__init__.py
Golang101Hacks/font/fontello.eot
Golang101Hacks/font/fontello.svg
Golang101Hacks/font/fontello.ttf
Golang101Hacks/font/fontello.woff
Golang101Hacks/img/__init__.py
Golang101Hacks/img/annotator-glyph-sprite.png
Golang101Hacks/img/annotator-icon-sprite.png
Golang101Hacks/img/apple-touch-icon.png
Golang101Hacks/img/cancelfullscreen.png
Golang101Hacks/img/close.png
Golang101Hacks/img/fullscreen.png
Golang101Hacks/img/loader.gif
Golang101Hacks/img/menu-icon.png
Golang101Hacks/img/save.png
Golang101Hacks/img/saved.png
Golang101Hacks/img/settings-s.png
Golang101Hacks/img/settings.png
Golang101Hacks/img/star.png
Golang101Hacks/js/__init__.py
Golang101Hacks/js/epub.js
Golang101Hacks/js/epub.min.js
Golang101Hacks/js/epub.min.map
Golang101Hacks/js/hooks.min.js
Golang101Hacks/js/hooks.min.map
Golang101Hacks/js/reader.js
Golang101Hacks/js/reader.js.map
Golang101Hacks/js/reader.min.js
Golang101Hacks/js/reader.min.map
Golang101Hacks/js/hooks/__init__.py
Golang101Hacks/js/hooks/extensions/__init__.py
Golang101Hacks/js/hooks/extensions/highlight.js
Golang101Hacks/js/libs/__init__.py
Golang101Hacks/js/libs/jquery.min.js
Golang101Hacks/js/libs/localforage.min.js
Golang101Hacks/js/libs/screenfull.js
Golang101Hacks/js/libs/screenfull.min.js
Golang101Hacks/js/libs/zip.min.js
Golang101Hacks/js/plugins/__init__.py
Golang101Hacks/js/plugins/hypothesis.js
Golang101Hacks/js/plugins/search.js
golang_101_hacks-2024.3.3.0.dist-info/METADATA
golang_101_hacks-2024.3.3.0.dist-info/WHEEL
golang_101_hacks-2024.3.3.0.dist-info/entry_points.txt
golang_101_hacks-2024.3.3.0.dist-info/top_level.txt
golang_101_hacks-2024.3.3.0.dist-info/RECORD
